sensormotion/__init__.py
sensormotion/gait.py
sensormotion/pa.py
sensormotion/peak.py
sensormotion/plot.py
sensormotion/signal.py
sensormotion/utils.py
sensormotion/version.py
sensormotion-1.1.5.dist-info/LICENSE
sensormotion-1.1.5.dist-info/METADATA
sensormotion-1.1.5.dist-info/WHEEL
sensormotion-1.1.5.dist-info/top_level.txt
sensormotion-1.1.5.dist-info/zip-safe
sensormotion-1.1.5.dist-info/RECORD
