Metadata-Version: 2.1
Name: sensormotion
Version: 1.1.5
Summary: Python package for analyzing sensor-collected human motion data (e.g. physical activity levels, gait dynamics)
Home-page: https://github.com/sho-87/sensormotion
Author: Simon Ho
Author-email: simonho.ubc@gmail.com
License: MIT
Project-URL: Documentation, http://sensormotion.readthedocs.io
Project-URL: Source, https://github.com/sho-87/sensormotion
Project-URL: Tracker, https://github.com/sho-87/sensormotion/issues
Keywords: gait accelerometer signal-processing walking actigraph physical-activity
Classifier: Development Status :: 5 - Production/Stable
Classifier: Intended Audience :: Science/Research
Classifier: License :: OSI Approved :: MIT License
Classifier: Operating System :: OS Independent
Classifier: Programming Language :: Python :: 3
Classifier: Topic :: Scientific/Engineering
Requires-Python: >=3
License-File: LICENSE
Requires-Dist: matplotlib
Requires-Dist: numpy
Requires-Dist: scipy
